robopy2/__init__.py
robopy2/kinematics.py
tests/__init__.py
tests/test_kinematics.py
robopy2-0.1.0.dist-info/LICENSE
robopy2-0.1.0.dist-info/METADATA
robopy2-0.1.0.dist-info/WHEEL
robopy2-0.1.0.dist-info/top_level.txt
robopy2-0.1.0.dist-info/RECORD
